{
    "31": [
        22,
        26,
        1,
        23,
        20,
        24,
        14
    ],
    "11": [
        21,
        24,
        3,
        31,
        13,
        26,
        0,
        23,
        20
    ],
    "13": [
        9,
        14,
        18,
        30,
        22,
        27,
        11
    ],
    "12": [
        29,
        14,
        10,
        21,
        25,
        30,
        27
    ],
    "7": [
        27,
        0,
        8,
        14
    ],
    "0": [
        6,
        0,
        3
    ],
    "10": [
        6,
        5,
        12,
        1,
        4,
        17,
        21,
        10,
        8
    ],
    "9": [
        5,
        12,
        29,
        21,
        15,
        30
    ],
    "8": [
        3,
        11,
        21,
        12,
        6,
        28,
        8,
        26,
        27
    ],
    "16": [
        25
    ],
    "14": [
        0,
        18,
        30
    ],
    "2": [
        16
    ],
    "6": [
        16,
        14,
        15,
        9
    ]
}